Metadata-Version: 2.1
Name: noompy
Version: 1.10
Summary: noompy is a simple minimalistic Excel API which helps you to "query" your .xls & .xlsx files. It supports SELECT and UPDATE statements as well as WHERE, AND and OR conditions. 
Home-page: https://github.com/salunkhe-ravi/noompy
Author: Ravi Salunkhe
Author-email: salunkhe.ravi@ymail.com
License: MIT
Download-URL: https://github.com/salunkhe-ravi/noompy/archive/v1.10.tar.gz
Keywords: noompy,excel,excel api,query excel
Platform: UNKNOWN
Classifier: Development Status :: 5 - Production/Stable
Classifier: Intended Audience :: Developers
Classifier: Topic :: Software Development :: Build Tools
Classifier: License :: OSI Approved :: MIT License
Classifier: Programming Language :: Python :: 3.6
Classifier: Programming Language :: Python :: 3.7
